douyin_scanner_mcp/__init__.py
douyin_scanner_mcp/config.py
douyin_scanner_mcp/main.py
douyin_scanner_mcp/scanner.py
douyin_scanner_mcp/js/__init__.py
douyin_scanner_mcp/js/douyin_items.js
douyin_scanner_mcp-0.1.3.dist-info/METADATA
douyin_scanner_mcp-0.1.3.dist-info/WHEEL
douyin_scanner_mcp-0.1.3.dist-info/entry_points.txt
douyin_scanner_mcp-0.1.3.dist-info/top_level.txt
douyin_scanner_mcp-0.1.3.dist-info/RECORD
