Metadata-Version: 2.4
Name: douyin-scanner-mcp
Version: 0.1.3
Summary: MCP client for Douyin Scanner with integrated scanning capabilities
Author: Your Name
Author-email: Your Name <your.email@example.com>
License: MIT
Project-URL: Homepage, https://github.com/yourusername/douyin-scanner-mcp
Project-URL: Bug Tracker, https://github.com/yourusername/douyin-scanner-mcp/issues
Classifier: Programming Language :: Python :: 3
Classifier: License :: OSI Approved :: MIT License
Classifier: Operating System :: OS Independent
Requires-Python: >=3.8
Requires-Dist: requests>=2.31.0
Requires-Dist: python-dotenv>=1.0.0
Requires-Dist: pydantic>=2.0.0
Requires-Dist: rich>=13.6.0
Requires-Dist: typer>=0.9.0
Requires-Dist: httpx>=0.24.0
Requires-Dist: aiohttp>=3.8.5
Requires-Dist: asyncio>=3.4.3
Requires-Dist: fastmcp>=0.1.0
Requires-Dist: playwright>=1.32.0
Dynamic: author
